numbertoword/__init__.py
numbertoword/currencies.py
numbertoword/currency.py
numbertoword/number_to_word.py
numbertoword/test.py
number_to_word-1.1.dist-info/LICENSE
number_to_word-1.1.dist-info/METADATA
number_to_word-1.1.dist-info/WHEEL
number_to_word-1.1.dist-info/top_level.txt
number_to_word-1.1.dist-info/RECORD
