Metadata-Version: 2.1
Name: number-to-word
Version: 1.1
Summary: number-to-word is a Python library for converting numbers into their written English or Arabic word equivalents.
Home-page: https://github.com/adelkhayata/number-to-word
Author: Adel Khayata
Author-email: adel@khayata.com
License: MIT
Classifier: Development Status :: 5 - Production/Stable
Classifier: Intended Audience :: Developers
Classifier: Topic :: Software Development :: Libraries
Classifier: License :: OSI Approved :: MIT License
Classifier: Programming Language :: Python :: 3
Classifier: Programming Language :: Python :: 3.6
Classifier: Programming Language :: Python :: 3.7
Classifier: Programming Language :: Python :: 3.8
Classifier: Programming Language :: Python :: 3.9
Classifier: Programming Language :: Python :: 3.10
Requires-Python: >=3.6
License-File: LICENSE
